[
  {
    "datetimeEpoch": 1665039600,
    "temp": 59.3,
    "windspeed": 5.2,
    "winddir": 313,
    "cloudcover": 15.4
  },
  {
    "datetimeEpoch": 1665043200,
    "temp": 58.3,
    "windspeed": 0,
    "winddir": 0,
    "cloudcover": 13.9
  },
  {
    "datetimeEpoch": 1665046800,
    "temp": 55.9,
    "windspeed": 1.7,
    "winddir": 20,
    "cloudcover": 13.9
  },
  {
    "datetimeEpoch": 1665050400,
    "temp": 55.2,
    "windspeed": 2.4,
    "winddir": 13,
    "cloudcover": 13.9
  },
  {
    "datetimeEpoch": 1665054000,
    "temp": 55.2,
    "windspeed": 0,
    "winddir": 0,
    "cloudcover": 13.9
  },
  {
    "datetimeEpoch": 1665057600,
    "temp": 55.4,
    "windspeed": 1.7,
    "winddir": 360,
    "cloudcover": 13.9
  },
  {
    "datetimeEpoch": 1665061200,
    "temp": 55.1,
    "windspeed": 2.6,
    "winddir": 353,
    "cloudcover": 24.4
  },
  {
    "datetimeEpoch": 1665064800,
    "temp": 54.4,
    "windspeed": 4.1,
    "winddir": 31,
    "cloudcover": 36.7
  },
  {
    "datetimeEpoch": 1665068400,
    "temp": 55.8,
    "windspeed": 4.2,
    "winddir": 47,
    "cloudcover": 48.5
  },
  {
    "datetimeEpoch": 1665072000,
    "temp": 57.6,
    "windspeed": 3,
    "winddir": 325,
    "cloudcover": 68.3
  },
  {
    "datetimeEpoch": 1665075600,
    "temp": 60,
    "windspeed": 0,
    "winddir": 0,
    "cloudcover": 65.8
  },
  {
    "datetimeEpoch": 1665079200,
    "temp": 65.1,
    "windspeed": 3.4,
    "winddir": 206,
    "cloudcover": 50.7
  },
  {
    "datetimeEpoch": 1665082800,
    "temp": 67.3,
    "windspeed": 5.6,
    "winddir": 275,
    "cloudcover": 45
  },
  {
    "datetimeEpoch": 1665086400,
    "temp": 71.5,
    "windspeed": 6.5,
    "winddir": 291,
    "cloudcover": 45
  },
  {
    "datetimeEpoch": 1665090000,
    "temp": 74.2,
    "windspeed": 11.7,
    "winddir": 291,
    "cloudcover": 24.4
  },
  {
    "datetimeEpoch": 1665093600,
    "temp": 75.4,
    "windspeed": 10.6,
    "winddir": 307,
    "cloudcover": 49.8
  },
  {
    "datetimeEpoch": 1665097200,
    "temp": 72.7,
    "windspeed": 10.8,
    "winddir": 296,
    "cloudcover": 45
  },
  {
    "datetimeEpoch": 1665100800,
    "temp": 73.4,
    "windspeed": 9.2,
    "winddir": 305,
    "cloudcover": 22
  },
  {
    "datetimeEpoch": 1665104400,
    "temp": 72.1,
    "windspeed": 8.1,
    "winddir": 313,
    "cloudcover": 45
  },
  {
    "datetimeEpoch": 1665108000,
    "temp": 67.1,
    "windspeed": 6.1,
    "winddir": 317,
    "cloudcover": 22
  },
  {
    "datetimeEpoch": 1665111600,
    "temp": 65.2,
    "windspeed": 7.4,
    "winddir": 317,
    "cloudcover": 25.3
  },
  {
    "datetimeEpoch": 1665115200,
    "temp": 62.7,
    "windspeed": 6.7,
    "winddir": 319,
    "cloudcover": 13.9
  },
  {
    "datetimeEpoch": 1665118800,
    "temp": 60.4,
    "windspeed": 5.8,
    "winddir": 317,
    "cloudcover": 13.9
  },
  {
    "datetimeEpoch": 1665122400,
    "temp": 59.9,
    "windspeed": 5.3,
    "winddir": 320,
    "cloudcover": 13.9
  }
]
